asyncmake/__init__.py
asyncmake/exec/__init__.py
asyncmake/exec/base.py
asyncmake/exec/make.py
asyncmake/parse/__init__.py
asyncmake/parse/base.py
asyncmake/parse/parser.py
asyncmake/search/__init__.py
asyncmake/search/base.py
asyncmake/search/searcher.py
asyncmake-0.1.4.dist-info/LICENSE
asyncmake-0.1.4.dist-info/WHEEL
asyncmake-0.1.4.dist-info/METADATA
asyncmake-0.1.4.dist-info/RECORD
